{"SolvesborgSnapphanegatan":{"lat":56.058325,"lon":14.5900155},"SolvesborgSkanevagen":{"lat":56.052742,"lon":14.5694331},"RonnebyVastervagen":{"lat":56.2417188,"lon":15.2677795},"RonnebyKarlshamnsvagen":{"lat":56.2297126,"lon":15.26109},"RonnebyBraknevagen":{"lat":56.2248739,"lon":15.1125307},"OlofstromOstra":{"lat":56.2778099,"lon":14.5309332},"KarlskronaFagelmara":{"lat":null,"lon":null},"KarlshamnJannebergsvagen":{"lat":56.1925656,"lon":14.8432685},"KarlshamnHinseleden":{"lat":56.1698813,"lon":14.8599254},"KarlshamnGustavstorpsvagen":{"lat":56.1673337,"lon":14.6825344},"OlofstromIsaksmala":{"lat":56.340498,"lon":14.5482484},"KarlskronaFridlevstad":{"lat":null,"lon":null},"LudvikaTunnelgatan":{"lat":60.1425307,"lon":15.1781288},"VansbroAlvgatan":{"lat":60.508327,"lon":14.2303212},"RattvikNyakersvagen":{"lat":60.8914628,"lon":15.110308},"LudvikaKommersvagen":{"lat":null,"lon":null},"HedemoraOsterbyvagen":{"lat":null,"lon":null},"HedemoraIvarshyttevagen":{"lat":null,"lon":null},"FalunTimmervagen":{"lat":null,"lon":null},"FalunGruvgatan":{"lat":null,"lon":null},"FalunFargvagen":{"lat":null,"lon":null},"BorlangeKupolen":{"lat":null,"lon":null},"LudvikaSnoavagen":{"lat":null,"lon":null},"RattvikFurudal":{"lat":null,"lon":null},"BorlangeBygatan":{"lat":null,"lon":null},"SoderhamnBradgardsgatan":{"lat":null,"lon":null},"SandvikenGavlevagen":{"lat":null,"lon":null},"LjusdalHudiksvallsvagen":{"lat":null,"lon":null},"HudiksvallKungsgatan":{"lat":null,"lon":null},"HoforsFaluvagen":{"lat":null,"lon":null},"GavleSolgardsgatan":{"lat":null,"lon":null},"GavleSatrahojden":{"lat":null,"lon":null},"GavleIndustrigatan":{"lat":null,"lon":null},"BollnasVaggatan":{"lat":null,"lon":null},"BollnasPostgrand":{"lat":null,"lon":null},"SoderhamnFlygvagen":{"lat":null,"lon":null},"GavleSodra":{"lat":null,"lon":null},"GavleStromsbrovagen":{"lat":null,"lon":null},"VarbergVeddige":{"lat":null,"lon":null},"VarbergBirger":{"lat":null,"lon":null},"LaholmMellbystrand":{"lat":null,"lon":null},"KungsbackaVarbergsvagen":{"lat":null,"lon":null},"KungsbackaAsa":{"lat":null,"lon":null},"HalmstadNissastigen":{"lat":null,"lon":null},"HalmstadLaholmsvagen":{"lat":null,"lon":null},"HalmstadGamla":{"lat":null,"lon":null},"FalkenbergSmidesvagen":{"lat":null,"lon":null},"FalkenbergIndustrivagen":{"lat":null,"lon":null},"FalkenbergPlankagardsvagen":{"lat":null,"lon":null},"FalkenbergAlvsered":{"lat":null,"lon":null},"AreJarpen":{"lat":null,"lon":null},"AreHallenvagen":{"lat":null,"lon":null},"StromsundHoting":{"lat":null,"lon":null},"HarjedalenParkgatan":{"lat":null,"lon":null},"HarjedalenSveg":{"lat":null,"lon":null},"HarjedalenVallarvagen":{"lat":null,"lon":null},"OstersundHagvagen":{"lat":null,"lon":null},"BergAsarna":{"lat":null,"lon":null},"NassjoSorangsvagen":{"lat":null,"lon":null},"VetlandaLasarettsgatan":{"lat":57.4199251,"lon":15.0906458},"VarnamoTrafikplats":{"lat":null,"lon":null},"VarnamoMalmovagen":{"lat":57.1695881,"lon":14.062076},"VarnamoFredsgatan":{"lat":57.1825784,"lon":14.0272239},"TranasOstra":{"lat":58.0328762,"lon":14.9941728},"TranasHagadalsgatan":{"lat":58.0288627,"lon":14.959465},"MullsjoBottnarydsvagen":{"lat":57.9025075,"lon":13.8525647},"JonkopingVarnamovagen":{"lat":57.7465227,"lon":14.1571175},"JonkopingJordbrovagen":{"lat":57.7676076,"lon":14.1534872},"JonkopingHerkulesvagen":{"lat":57.7712302,"lon":14.1742152},"JonkopingEkhagsringen":{"lat":57.7743043,"lon":14.2213668},"HaboKrakerydsvagen":{"lat":57.9120333,"lon":14.0933425},"GislavedJarnvagsgatan":{"lat":57.3049892,"lon":13.5417557},"EksjoTuvangsvagen":{"lat":null,"lon":null},"NassjoBrogatan":{"lat":57.6509051,"lon":14.7012505},"VetlandaNygatan":{"lat":57.4044764,"lon":15.5016566},"VetlandaStorgatan":{"lat":57.4279612,"lon":15.0801908},"VetlandaVetlanda":{"lat":null,"lon":null},"NassjoGjutaregatan":{"lat":57.6494925,"lon":14.6940548},"VetlandaKorsberga":{"lat":null,"lon":null},"VetlandaHallingevagen":{"lat":57.4287465,"lon":15.0494321},"VimmerbySodra":{"lat":57.6601933,"lon":15.8509708},"VimmerbyNorrgardsgatan":{"lat":57.6773509,"lon":15.8526211},"KalmarHusmorsvagen":{"lat":56.7242249,"lon":16.3017878},"KalmarFunkabovagen":{"lat":56.6882329,"lon":16.339942},"KalmarEngelska":{"lat":56.6965067,"lon":16.3268891},"HultsfredN":{"lat":57.5012403,"lon":15.8187738},"VastervikVasterviksv":{"lat":57.8919342,"lon":16.4027716},"TorsasAllfargatan":{"lat":56.4122377,"lon":16.0009094},"NybroOrrefors":{"lat":null,"lon":null},"NybroAlsterbro":{"lat":null,"lon":null},"AlmhultTorvstrovagen":{"lat":56.5468829,"lon":14.1568264},"VaxjoVingavagen":{"lat":56.9045685,"lon":14.8008158},"VaxjoMorners":{"lat":56.8896508,"lon":14.7959823},"VaxjoMornersvag":{"lat":56.8864604,"lon":14.7673871},"MarkarydDrottninggatan":{"lat":56.4693284,"lon":13.6018241},"LjungbyMarta":{"lat":56.8336492,"lon":13.934587},"AlmhultDanska":{"lat":56.5556483,"lon":14.1452368},"VaxjoMinkvagen":{"lat":56.9100489,"lon":14.8323809},"UppvidingeLenhovda":{"lat":56.9988449,"lon":15.2847873},"UppvidingeJarnvagsgatan":{"lat":56.9744818,"lon":15.6535956},"PiteaJavrevagen":{"lat":65.1556772,"lon":21.5214447},"PiteaHammarvagen":{"lat":65.3343705,"lon":21.4201947},"PajalaKengisgatan":{"lat":67.2115196,"lon":23.3733469},"LuleaMidgardsvagen":{"lat":65.5969188,"lon":22.1460522},"LuleaHallbruksgatan":{"lat":65.5818094,"lon":22.2060372},"LuleaBanvagen":{"lat":65.6098509,"lon":22.120636},"HaparandaNorra":{"lat":65.8388722,"lon":24.1218182},"HaparandaKraftvagen":{"lat":65.8440467,"lon":24.1242847},"HaparandaAhlmarksv":{"lat":65.8439781,"lon":24.116267},"HaparandaVastra":{"lat":65.8411765,"lon":24.1275176},"OrebroVintrosasanna":{"lat":null,"lon":null},"OrebroNejlikegatan":{"lat":59.2949975,"lon":15.1639282},"OrebroKarlsundsgatan":{"lat":null,"lon":null},"NoraStorgatan":{"lat":59.5091854,"lon":15.0213161},"LindesbergBergsmansgatan":{"lat":59.5977099,"lon":15.2239839},"KumlaStenevagen":{"lat":59.1253651,"lon":15.1131426},"KarlskogaHasangsvagen":{"lat":59.3225758,"lon":14.4825875},"HalleforsKyllervagen":{"lat":59.7774036,"lon":14.5223142},"KarlskogaRosendalskorsningen":{"lat":null,"lon":null},"OrebroVaruvagen":{"lat":59.2152027,"lon":15.140344},"KarlskogaVarmlandsvagen":{"lat":59.3277133,"lon":14.5112001},"HallsbergLanggatan":{"lat":59.0683463,"lon":15.1075657},"NorrkopingStockholmsvagen":{"lat":58.6265263,"lon":16.1586828},"NorrkopingKoppargatan":{"lat":58.6382353,"lon":16.1564636},"NorrkopingBergslagsvagen":{"lat":58.58119,"lon":15.9174145},"MotalaVintergatan":{"lat":58.5382604,"lon":15.01623},"MotalaSodra":{"lat":58.5373783,"lon":15.0533042},"MjolbyRunvagen":{"lat":58.3650654,"lon":15.2940699},"MjolbyKungsvagen":{"lat":58.3260435,"lon":15.1287715},"LinkopingTorvingegatan":{"lat":58.4187507,"lon":15.6786404},"LinkopingTallboda":{"lat":null,"lon":null},"LinkopingLaskolvsgatan":{"lat":58.3988637,"lon":15.6900956},"LinkopingEkholmsvagen":{"lat":58.3793453,"lon":15.6854302},"KindaVastra":{"lat":57.984621,"lon":15.6175771},"FinspangOstermalmsvagen":{"lat":58.7140661,"lon":15.8195578},"FinspangBergslagsvagen":{"lat":58.7057918,"lon":15.76753},"ValdemarsvikKyrkangsvagen":{"lat":58.3330262,"lon":16.4518941},"LinkopingIndustrigatan":{"lat":58.4198092,"lon":15.6041831},"LinkopingLinghem":{"lat":null,"lon":null},"LundPorfyrvagen":{"lat":55.6943215,"lon":13.2213951},"YstadMissunavagen":{"lat":null,"lon":null},"TrelleborgStavstensvagen":{"lat":55.3757441,"lon":13.1318282},"TomelillaOstergatan":{"lat":55.5439515,"lon":13.9543449},"SvalovRonnebergsvagen":{"lat":55.9048665,"lon":13.0485133},"SimrishamnFabriksgatan":{"lat":55.5456954,"lon":14.3306487},"OsbySaggatan":{"lat":56.479236,"lon":14.0980013},"MalmoSvagertorp":{"lat":null,"lon":null},"MalmoSallerupsvagen":{"lat":55.6030425,"lon":13.0303004},"MalmoRamels":{"lat":55.5776672,"lon":13.0503768},"MalmoMunkhattegatan":{"lat":55.5697498,"lon":13.0125691},"MalmoLundavagen":{"lat":55.6397154,"lon":13.0876718},"MalmoLinn\u00e9gatan":{"lat":null,"lon":null},"MalmoLantmannagatan":{"lat":55.5881218,"lon":13.0195417},"MalmoEriksfaltsgatan":{"lat":55.5653774,"lon":13.0215425},"MalmoCypressvagen":{"lat":55.5717449,"lon":13.0393815},"MalmoBellevuevagen":{"lat":55.5771334,"lon":12.9637565},"LundTrollebergsvagen":{"lat":55.7030622,"lon":13.1670996},"LundMejerigatan":{"lat":55.6356435,"lon":13.4915416},"LundBondevagen":{"lat":55.7140897,"lon":13.1716124},"LandskronaMalmovagen":{"lat":55.8717649,"lon":12.8548245},"KristianstadLangebrogatan":{"lat":56.0240535,"lon":14.1547814},"KristianstadFregattvagen":{"lat":55.9346528,"lon":14.2812467},"KristianstadFjalkinge":{"lat":56.0317515,"lon":14.2088702},"KristianstadBlekingevagen":{"lat":56.0282839,"lon":14.2064236},"KlippanLisakravagen":{"lat":56.2031339,"lon":13.1092643},"KavlingeMarknadsvagen":{"lat":55.7701306,"lon":12.9906755},"KavlingeBogesholmsvagen":{"lat":55.7977731,"lon":13.0992882},"HorbyRingsjovagen":{"lat":55.849819,"lon":13.6478945},"HoganasLangarodsvagen":{"lat":56.1981408,"lon":12.5575607},"HelsingborgRegementsvagen":{"lat":56.064856,"lon":12.7200314},"HelsingborgRannarbanan":{"lat":56.0168987,"lon":12.7346706},"HelsingborgFurutorpsgatan":{"lat":56.0388185,"lon":12.7109257},"HassleholmTyringe":{"lat":null,"lon":null},"HassleholmSvedjemarksgatan":{"lat":56.1487481,"lon":13.787286},"HassleholmMackgatan":{"lat":56.1699312,"lon":13.8195207},"HassleholmBjarnum":{"lat":null,"lon":null},"EslovYstadsvagen":{"lat":55.8297204,"lon":13.3057091},"EslovTreharadsvagen":{"lat":55.8327721,"lon":13.3013017},"EslovGardstanga":{"lat":55.7177687,"lon":13.5237873},"AngelholmVerkstadsgatan":{"lat":56.2498429,"lon":12.8904078},"AngelholmKlippanvagen":{"lat":56.253097,"lon":13.0012516},"AngelholmHelsingborgsvagen":{"lat":56.224037,"lon":12.85882},"HoorGunnarp":{"lat":null,"lon":null},"AstorpVastra":{"lat":56.1346594,"lon":13.0325221},"AngelholmNordalagatan":{"lat":56.2533824,"lon":12.910416},"KlippanStorgatan":{"lat":56.1392094,"lon":13.1144514},"HoorNya":{"lat":55.9263561,"lon":13.5455654},"LandskronaForeningsgatan":{"lat":55.8736669,"lon":12.8454642},"HelsingborgValavagen":{"lat":56.0646294,"lon":12.7481115},"AngelholmOstra":{"lat":56.2343761,"lon":12.8767168},"LandskronaForetagsvagen":{"lat":55.8742953,"lon":12.8853056},"HoorSodergatan":{"lat":55.9282635,"lon":13.5437181},"KristianstadSkolgatan":{"lat":56.0621029,"lon":14.0254137},"KavlingeHandlarn":{"lat":null,"lon":null},"TrelleborgAlstad":{"lat":null,"lon":null},"MalmoNya":{"lat":55.6079887,"lon":12.9946611},"KristianstadYngsjo":{"lat":55.8832752,"lon":14.2292556},"BurlovArlov":{"lat":null,"lon":null},"MalmoDerbyvagen":{"lat":55.5780141,"lon":13.0663784},"StrangnasEskilstunavagen":{"lat":59.3765759,"lon":17.013555},"NykopingNorrkopingsvagen":{"lat":58.7496386,"lon":16.9838879},"EskilstunaGillbergaplan":{"lat":null,"lon":null},"EskilstunaArbygatan":{"lat":59.3836719,"lon":16.5235542},"EskilstunaAlbertina":{"lat":59.3735165,"lon":16.4704996},"NykopingLennings":{"lat":58.7591343,"lon":17.0328442},"GnestaDansutvagen":{"lat":59.0386532,"lon":17.3113719},"VarmdoAfrodites":{"lat":59.3121594,"lon":18.4241656},"VallentunaFagelsangsvagen":{"lat":59.5154438,"lon":18.0904983},"VallentunaAngarnsvagen":{"lat":59.5306978,"lon":18.1031897},"VasbyStockholmsvagen":{"lat":59.49725,"lon":17.9212344},"UpplandsBroBrunna":{"lat":null,"lon":null},"TyresoIndustrivagen":{"lat":59.2462922,"lon":18.2196859},"TabyEnhagsvagen":{"lat":59.4382164,"lon":18.0553691},"TabyBergtorpsvagen":{"lat":59.4638661,"lon":18.0710241},"StockholmVasaloppsvagen":{"lat":59.2928543,"lon":17.9622131},"StockholmVallingby":{"lat":null,"lon":null},"StockholmSpanga":{"lat":59.3871774,"lon":17.9055537},"StockholmRagsvedsvagen":{"lat":59.2562036,"lon":18.0212929},"StockholmLagavagen":{"lat":59.2773334,"lon":18.130561},"StockholmFrihamnen":{"lat":null,"lon":null},"StockholmElektravagen":{"lat":59.2936841,"lon":18.0081327},"StockholmEldholmsbacken":{"lat":59.276168,"lon":17.9118398},"StockholmBredangsvagen":{"lat":59.2923805,"lon":17.9462894},"StockholmArsta":{"lat":59.2951086,"lon":18.0557889},"SollentunaKanalvagen":{"lat":59.4227202,"lon":17.9442132},"SodertaljeErikshallsgatan":{"lat":59.187735,"lon":17.6185632},"SigtunaMarsta":{"lat":null,"lon":null},"SalemRonninge":{"lat":null,"lon":null},"OsterakerRallarvagen":{"lat":59.4808869,"lon":18.2842226},"NorrtaljeStockholmsvagen":{"lat":59.7486031,"lon":18.6874548},"NorrtaljeNorrtaljevagen":{"lat":59.8405549,"lon":18.6653789},"NackaSaltsjobaden":{"lat":null,"lon":null},"LidingoSkarsatra":{"lat":59.3439659,"lon":18.1620062},"JarfallaSkalbyvagen":{"lat":59.3906592,"lon":17.845011},"HuddingeSegeltorp":{"lat":null,"lon":null},"HuddingeHuddingevagen":{"lat":59.2400522,"lon":17.9789797},"HaningeHanden":{"lat":null,"lon":null},"BotkyrkaTuna":{"lat":null,"lon":null},"BotkyrkaTumba":{"lat":null,"lon":null},"BotkyrkaTullinge":{"lat":null,"lon":null},"BotkyrkaNorsborg":{"lat":null,"lon":null},"VallentunaIndustrivagen":{"lat":59.5316737,"lon":18.0786838},"NackaVattenverksvagen":{"lat":59.306182,"lon":18.1829714},"NackaKlintvagen":{"lat":59.3152551,"lon":18.2282436},"VarmdoBlekangsvagen":{"lat":59.3280861,"lon":18.3921485},"NackaSkvaltans":{"lat":59.3111388,"lon":18.1651192},"NackaKanholmsvagen":{"lat":59.3240182,"lon":18.2567545},"VarmdoVarmdo":{"lat":59.3968569,"lon":18.4506665},"VarmdoGustavsberg":{"lat":null,"lon":null},"UpplandsBroKungsangen":{"lat":null,"lon":null},"UpplandsBroBro":{"lat":59.4925655,"lon":17.6226635},"HuddingeVarby":{"lat":59.2631835,"lon":17.8849554},"UppsalaHogsta":{"lat":59.9769938,"lon":17.5764088},"UppsalaAterbruksgatan":{"lat":null,"lon":null},"OsthammarDannemoravagen":{"lat":60.1975335,"lon":17.8670277},"EnkopingMastergatan":{"lat":59.6449788,"lon":17.0943412},"AlvkarlebyBrannmovagen":{"lat":60.5644875,"lon":17.4594208},"UppsalaSkebogatan":{"lat":59.8725085,"lon":17.6041045},"UppsalaKungsgatan":{"lat":59.8461253,"lon":17.6662881},"TierpVastra":{"lat":60.3377931,"lon":17.5201824},"UppsalaFullero":{"lat":59.9534171,"lon":17.6778384},"TierpCentralgatan":{"lat":60.3424904,"lon":17.5172689},"SaffleKungsgatan":{"lat":59.1305579,"lon":12.9204043},"SaffleKarlavagnsvagen":{"lat":59.1277539,"lon":12.8837375},"KristinehamnKarlstadsvagen":{"lat":59.3159223,"lon":14.099778},"KarlstadVentilgatan":{"lat":59.3822132,"lon":13.4612421},"KarlstadVaxnas":{"lat":59.3815657,"lon":13.4899901},"HagforsGorsjovagen":{"lat":60.0424524,"lon":13.7038191},"GrumsSveagatan":{"lat":59.3535316,"lon":13.1128741},"ForshagaFramgardsvagen":{"lat":59.539637,"lon":13.4842735},"ArvikaMotterudsvagen":{"lat":59.646891,"lon":12.6223487},"ArjangSmedgatan":{"lat":59.3974334,"lon":12.1364123},"KristinehamnStationsgatan":{"lat":59.3157315,"lon":14.1045142},"EdaMorokulien":{"lat":null,"lon":null},"UmeaTankvagen":{"lat":63.8191658,"lon":20.2488462},"UmeaRodbergsvagen":{"lat":63.8433586,"lon":20.2051598},"UmeaFormvagen":{"lat":63.8500646,"lon":20.3086322},"SkellefteaTjarnvagen":{"lat":64.7375466,"lon":20.9594854},"LyckseleBla":{"lat":64.7582281,"lon":18.1669634},"SkellefteaJorn":{"lat":null,"lon":null},"UmeaUmea":{"lat":null,"lon":null},"SundsvallBirsta":{"lat":null,"lon":null},"SollefteaNorra":{"lat":63.6640367,"lon":16.5749427},"OrnskoldsvikDomsjo":{"lat":63.2600113,"lon":18.7460533},"OrnskoldsvikBangatan":{"lat":63.2888154,"lon":18.705375},"HarnosandJarnvagsgatan":{"lat":62.6323046,"lon":17.9267639},"VasterasFredriksbergsgatan":{"lat":59.6042684,"lon":16.488866},"VasterasFaltmatargatan":{"lat":59.6143459,"lon":16.6086204},"SalaOstra":{"lat":59.9155426,"lon":16.6152964},"KopingNibblesbacken":{"lat":null,"lon":null},"FagerstaFloravagen":{"lat":60.0061295,"lon":15.8234859},"VasterasLangangsvagen":{"lat":59.588778,"lon":16.4375332},"SalaVasbygatan":{"lat":59.9215723,"lon":16.6142151},"HallstahammarVasterasvagen":{"lat":59.5967172,"lon":16.3344857},"VargardaWallentinsvagen":{"lat":58.0373634,"lon":12.7972806},"VaraTorggatan":{"lat":58.2999475,"lon":13.1858533},"UlricehamnBorasvagen":{"lat":57.798771,"lon":13.4132019},"UddevallaVastgotavagen":{"lat":58.352245,"lon":11.9582405},"UddevallaRotvik":{"lat":null,"lon":null},"UddevallaHerrestad":{"lat":58.341174,"lon":11.827673},"UddevallaBastiongatan":{"lat":58.3486524,"lon":11.9195782},"TrollhattanVarviksvagen":{"lat":58.2925672,"lon":12.2977454},"TrollhattanLextorpsvagen":{"lat":null,"lon":null},"TrollhattanKardanvagen":{"lat":null,"lon":null},"TrollhattanGardhemsvagen":{"lat":null,"lon":null},"TjornMallbyvagen":{"lat":null,"lon":null},"TjornFagerfjall":{"lat":null,"lon":null},"StenungsundSodra":{"lat":null,"lon":null},"SkovdeMariestadsvagen":{"lat":null,"lon":null},"SkovdeGustav":{"lat":null,"lon":null},"PartilleG":{"lat":null,"lon":null},"OrustSvanesund":{"lat":null,"lon":null},"MunkedalUddarne":{"lat":null,"lon":null},"MolndalLindome":{"lat":null,"lon":null},"MolndalLammevallsgatan":{"lat":null,"lon":null},"MarkHyssna":{"lat":null,"lon":null},"MariestadBjornbarsvagen":{"lat":null,"lon":null},"LysekilKontorsvagen":{"lat":null,"lon":null},"EdetGoteborgsvagen":{"lat":null,"lon":null},"KungalvGymnasiegatan":{"lat":null,"lon":null},"KungalvChristian":{"lat":null,"lon":null},"HarrydaMetallvagen":{"lat":null,"lon":null},"GullspangHova":{"lat":null,"lon":null},"GoteneLundangsgatan":{"lat":null,"lon":null},"GoteborgTiderakningsgatan":{"lat":null,"lon":null},"GoteborgStureplatsen":{"lat":null,"lon":null},"GoteborgSave":{"lat":null,"lon":null},"GoteborgSankt":{"lat":null,"lon":null},"GoteborgOlofstorp":{"lat":null,"lon":null},"GoteborgHisings":{"lat":null,"lon":null},"GoteborgGustaf":{"lat":null,"lon":null},"GoteborgA":{"lat":null,"lon":null},"GoteborgAskim":{"lat":null,"lon":null},"GoteborgAngered":{"lat":null,"lon":null},"FalkopingNordmannagatan":{"lat":null,"lon":null},"FalkopingFredsgatan":{"lat":null,"lon":null},"DalsEdJordbrovagen":{"lat":null,"lon":null},"BorasKatrinedalsgatan":{"lat":null,"lon":null},"BorasAlgardsvagen":{"lat":null,"lon":null},"BengtsforsEkagatan":{"lat":null,"lon":null},"AmalVanersborgsvagen":{"lat":null,"lon":null},"AlingsasBorgens":{"lat":null,"lon":null},"SvenljungaOverlida":{"lat":null,"lon":null},"AlingsasKungalvsvagen":{"lat":null,"lon":null},"BorasSexdrega":{"lat":null,"lon":null},"TrollhattanGrafitvagen":{"lat":null,"lon":null},"BorasViskafors":{"lat":null,"lon":null},"SvenljungaMjoback":{"lat":null,"lon":null},"PartilleGamla":{"lat":null,"lon":null},"HarrydaGamla":{"lat":null,"lon":null},"AlingsasPumpgatan":{"lat":null,"lon":null},"LerumAlmekarrsvagen":{"lat":null,"lon":null},"KungalvSmedmastaregatan":{"lat":null,"lon":null},"LerumSjovik":{"lat":null,"lon":null},"SkovdeIgelstorp":{"lat":null,"lon":null},"UddevallaHogstorp":{"lat":null,"lon":null},"VasterasStockholmsvagen":{"lat":59.6087494,"lon":16.6307512},"VasterasHallamotet":{"lat":59.6102597,"lon":16.6292204},"MarkHorred":{"lat":null,"lon":null},"VarbergVarnamovagen":{"lat":57.1232051,"lon":12.2870067},"LinkopingVaringagatan":{"lat":58.4158236,"lon":15.6423159},"AngelholmHjarnarp":{"lat":null,"lon":null},"SollentunaRudbecksvagen":{"lat":null,"lon":null},"SodertaljeBergaholmsvagen":{"lat":59.207042,"lon":17.6478129},"UppsalaSvartbacksgatan":{"lat":59.873864,"lon":17.6255232},"TibroVarsasvagen":{"lat":58.4226426,"lon":14.1390281},"StromstadOslovagen":{"lat":null,"lon":null},"MellerudKornsjogatan":{"lat":null,"lon":null},"LidkopingStrandgatan":{"lat":null,"lon":null},"LidkopingRorstrandsgatan":{"lat":null,"lon":null},"LidkopingHamngatan":{"lat":null,"lon":null},"LerumGoteborgsvagen":{"lat":null,"lon":null},"KungalvRollsbovagen":{"lat":null,"lon":null},"KungalvLilla":{"lat":null,"lon":null},"HjoFalkopingsvagen":{"lat":null,"lon":null},"GoteborgTorslanda":{"lat":null,"lon":null},"FalkopingWarodells":{"lat":null,"lon":null},"BorasSkaraborgsvagen":{"lat":null,"lon":null},"BorasRoasjovagen":{"lat":null,"lon":null},"AlingsasGotaplan":{"lat":null,"lon":null},"SkovdeNorregardsvagen":{"lat":null,"lon":null},"GoteborgPolstjarnegatan":{"lat":null,"lon":null},"BorasGanghestersvagen":{"lat":null,"lon":null},"AngelholmStrovelstorp":{"lat":null,"lon":null},"AngelholmSkalderviken":{"lat":null,"lon":null},"TjornKallekarr":{"lat":null,"lon":null},"SkovdeTidan":{"lat":null,"lon":null},"HudiksvallVastansjo":{"lat":null,"lon":null},"TrelleborgStrandgatan":{"lat":55.3736075,"lon":13.1491013},"VanersborgGropbovagen":{"lat":null,"lon":null},"SkovdeTidans":{"lat":58.5728487,"lon":14.0073972}}